Workbook

Sheet BDD unique
A1: TABLE SALARIE
A2: matricule | B2: nom | C2: prénom | D2: date naissance | E2: fonction | F2: salaire (brut)
A3: 1 | B3: Martin | C3: Paul | D3: 21530 | E3: ingénieur | F3: 4000
A4: 2 | B4: Bernard | C4: Sébastien | D4: 27437 | E4: technicien | F4: 2000
A5: 3 | B5: Domenech | C5: Raymon | D5: 19371 | E5: chef de projet | F5: 5000
A6: 4 | B6: Chirac | C6: Bernadette | D6: 30918 | E6: secrétaire | F6: 2500
A7: 5 | B7: Hollande | C7: François | D7: 18305 | E7: PDG | F7: 10000
A8: 6 | B8: Vaillant | C8: Paul | D8: 29231 | E8: commercial | F8: 2800
A9: 7 | B9: Faure | C9: Michel | D9: 27637 | E9: commercial | F9: 3000
A10: 8 | B10: Huster | C10: Françis | D10: 29638 | E10: commercial | F10: 2600
A12: TABLE PRODUIT
A13: id | B13: nom | C13: prix vente | D13: prix achat
A14: 1 | B14: Peugeot 406 | C14: 21000 | D14: 19000
A15: 2 | B15: BMW série 3 | C15: 32000 | D15: 31000
A16: 3 | B16: Renault mégane | C16: 15000 | D16: 12000
A17: 4 | B17: Renault clio | C17: 10000 | D17: 7000
A19: Table Entreprise
A20: nom | B20: adresse | C20: CP | D20: VILLE | E20: n°SIRET
A21: Concessionnaire Senghor | B21: Place Pierre Beregovoy | C21: 78200 | D21: MAGNANVILLE | E21: 15478652333214

Sheet fiche de paye
B1: BULLETIN DE PAIE - CADRE
B2: EMPLOYEUR: | G2: SALARIE:
B3: Nom: | D3: ='BDD unique'!A21 -> Concessionnaire Senghor | G3: matricule du salarié : | I3: 5
B4: Adresse: | D4: ='BDD unique'!B21 -> Place Pierre Beregovoy | G4: Nom et Prénom: | I4: =CONCATENATE(VLOOKUP(I3,'BDD unique'!A3:F10,2,FALSE())," ",VLOOKUP(I3,'BDD unique'!A3:F10,3,FALSE())) -> Hollande François
B5: CP et Ville : | D5: =CONCATENATE('BDD unique'!C21," ",'BDD unique'!D21) -> 78200 MAGNANVILLE | G5: Date naissance | I5: =VLOOKUP(I3,'BDD unique'!A3:F10,4,FALSE()) -> 18305
B6: Numéro SIRET: | D6: ='BDD unique'!E21 -> 15478652333214 | G6: fonction | I6: =VLOOKUP(I3,'BDD unique'!A3:F10,5,FALSE()) -> PDG
B9: SALAIRE BRUT | G9: =VLOOKUP(I3,'BDD unique'!A3:F10,6,FALSE()) -> 10000
B13: COTISATIONS | F13: PART SALARIALE | I13: PART PATRONALE
F14: Base | G14: Taux | H14: Montant | I14: Base | J14: Taux | K14: Montant
B15: CSG non déductible | F15: =$G$9*97% -> 9700 | G15: 0.024 | H15: =F15*G15 -> 232.8
B16: CRDS non déductible | F16: =$G$9*97% -> 9700 | G16: 0.005 | H16: =F16*G16 -> 48.5
B17: Csg déductible | F17: =$G$9*97% -> 9700 | G17: 0.051 | H17: =F17*G17 -> 494.7
B18: Sécurité sociale
B19: Assurance maladie | F19: =$G$9 -> 10000 | G19: 0.0075 | H19: =F19*G19 -> 75 | I19: =$G$9 -> 10000 | J19: 0.128 | K19: =I19*J19 -> 1280
B20: Assurance veuvage | F20: =$G$9 -> 10000 | G20: 0.001 | H20: =F20*G20 -> 10
B21: Assurance vieillesse
B22: AV déplafonée | F22: =$G$9 -> 10000 | G22: 0.0655 | H22: =F22*G22 -> 655 | I22: =$G$9 -> 10000 | J22: 0.016 | K22: =I22*J22 -> 160
B23: AV plafonnée | I23: =IF(I9>0,I9,G9) -> 10000 | J23: 0.082 | K23: =I23*J23 -> 820
B24: Accidents du travail | I24: =$G$9 -> 10000 | J24: 0.073 | K24: =I24*J24 -> 730
B25: Allocation familiales | I25: =$G$9 -> 10000 | J25: 0.054 | K25: =I25*J25 -> 540
B26: Aide au logement
B27: AL déplafonée | I27: =$G$9 -> 10000 | J27: 0.004 | K27: =I27*J27 -> 40
B28: AL plafonnée | I28: =$G$9 -> 10000 | J28: 0.001 | K28: =I28*J28 -> 10
B29: ASSEDIC
B30: Assurance chômage tranche B | F30: =IF(I9>0,I9,0) -> 0 | G30: 0.024 | H30: =F30*G30 -> 0 | I30: =F30 -> 0 | J30: 0.04 | K30: =I30*J30 -> 0
B31: Assurance chômage tranche AGS (FNGS) | I31: =$G$9 -> 10000 | J31: 0.004 | K31: =I31*J31 -> 40
B32: Caisse de retraite (cadre)
B33: Retraite complémentaire et AGFF tranche B | F33: =F30 -> 0 | G33: 0.084 | H33: =F33*G33 -> 0 | I33: =F33 -> 0 | J33: 0.138 | K33: =I33*J33 -> 0
B34: APEC | F34: =$G$9 -> 10000 | G34: 0.00024 | H34: =F34*G34 -> 2.4 | I34: =$G$9 -> 10000 | J34: 0.00036 | K34: =I34*J34 -> 3.6
B35: Assurance décès des cadres | I35: =$G$9 -> 10000 | J35: 0.015 | K35: =I35*J35 -> 150
B36: CET | F36: =$G$9 -> 10000 | G36: 0.0013 | H36: =F36*G36 -> 13 | I36: =$G$9 -> 10000 | J36: 0.0022 | K36: =I36*J36 -> 22
B37: TOTAL des cotisations | H37: =SUM(H15:H36) -> 1531.4 | K37: =SUM(K15:K36) -> 3795.6
H41: Net à payer | K41: =G9-H37 -> 8468.6
H43: Salaire net imposable | K43: =K41+H15 -> 8701.4
B45: A CONSERVER SANS LIMITATION DE DUREE

Sheet Vente
A1: MODULE VENTE | M1: ='BDD unique'!A14 -> 1 | N1: ='BDD unique'!B14 -> Peugeot 406 | O1: =CONCATENATE(M1," : ",N1) -> 1 : Peugeot 406 | Q1: ='BDD unique'!A8 -> 6 | R1: ='BDD unique'!B8 -> Vaillant | S1: ='BDD unique'!C8 -> Paul | T1: =CONCATENATE(Q1," : ",R1," ",S1) -> 6 : Vaillant Paul
M2: ='BDD unique'!A15 -> 2 | N2: ='BDD unique'!B15 -> BMW série 3 | O2: =CONCATENATE(M2," : ",N2) -> 2 : BMW série 3 | Q2: ='BDD unique'!A9 -> 7 | R2: ='BDD unique'!B9 -> Faure | S2: ='BDD unique'!C9 -> Michel | T2: =CONCATENATE(Q2," : ",R2," ",S2) -> 7 : Faure Michel
A3: Sélectionnez le produit vendu | M3: ='BDD unique'!A16 -> 3 | N3: ='BDD unique'!B16 -> Renault mégane | O3: =CONCATENATE(M3," : ",N3) -> 3 : Renault mégane | Q3: ='BDD unique'!A10 -> 8 | R3: ='BDD unique'!B10 -> Huster | S3: ='BDD unique'!C10 -> Françis | T3: =CONCATENATE(Q3," : ",R3," ",S3) -> 8 : Huster Françis
A4: saisir la qté vendu | M4: ='BDD unique'!A17 -> 4 | N4: ='BDD unique'!B17 -> Renault clio | O4: =CONCATENATE(M4," : ",N4) -> 4 : Renault clio
A5: Sélectionnez le commercial
A9: Historique des ventes
A10: date vente | B10: n° produit vendu | C10: quantité vendu | D10: n° commercial | E10: Prix unitaire vente | F10: Prix total
A11: 42009 | B11: 2 | C11: 2 | D11: 7 | E11: =VLOOKUP(B11,'BDD unique'!$A$14:$D$17,3,FALSE()) -> 32000 | F11: =E11*C11 -> 64000
A12: 42010 | B12: 1 | C12: 2 | D12: 8 | E12: =VLOOKUP(B12,'BDD unique'!$A$14:$D$17,3,FALSE()) -> 21000 | F12: =E12*C12 -> 42000
A13: 42011 | B13: 3 | C13: 15 | D13: 6 | E13: =VLOOKUP(B13,'BDD unique'!$A$14:$D$17,3,FALSE()) -> 15000 | F13: =E13*C13 -> 225000
A14: 42012 | B14: 4 | C14: 10 | D14: 6 | E14: =VLOOKUP(B14,'BDD unique'!$A$14:$D$17,3,FALSE()) -> 10000 | F14: =E14*C14 -> 100000
A15: 42013 | B15: 1 | C15: 10 | D15: 8 | E15: =VLOOKUP(B15,'BDD unique'!$A$14:$D$17,3,FALSE()) -> 21000 | F15: =E15*C15 -> 210000
A16: 42014 | B16: 2 | C16: 3 | D16: 8 | E16: =VLOOKUP(B16,'BDD unique'!$A$14:$D$17,3,FALSE()) -> 32000 | F16: =E16*C16 -> 96000
A17: 42015 | B17: 1 | C17: 4 | D17: 7 | E17: =VLOOKUP(B17,'BDD unique'!$A$14:$D$17,3,FALSE()) -> 21000 | F17: =E17*C17 -> 84000
A18: 42016 | B18: 4 | C18: 10 | D18: 8 | E18: =VLOOKUP(B18,'BDD unique'!$A$14:$D$17,3,FALSE()) -> 10000 | F18: =E18*C18 -> 100000
A19: 42017 | B19: 1 | C19: 10 | D19: 7 | E19: =VLOOKUP(B19,'BDD unique'!$A$14:$D$17,3,FALSE()) -> 21000 | F19: =E19*C19 -> 210000
A20: 42018 | B20: 2 | C20: 3 | D20: 6 | E20: =VLOOKUP(B20,'BDD unique'!$A$14:$D$17,3,FALSE()) -> 32000 | F20: =E20*C20 -> 96000
A21: 42019 | B21: 3 | C21: 5 | D21: 6 | E21: =VLOOKUP(B21,'BDD unique'!$A$14:$D$17,3,FALSE()) -> 15000 | F21: =E21*C21 -> 75000
A22: 42019 | B22: 4 | C22: 3 | D22: 6 | E22: =VLOOKUP(B22,'BDD unique'!$A$14:$D$17,3,FALSE()) -> 10000 | F22: =E22*C22 -> 30000
A23: 42025 | B23: 1 | C23: 10 | D23: 6 | E23: =VLOOKUP(B23,'BDD unique'!$A$14:$D$17,3,FALSE()) -> 21000 | F23: =E23*C23 -> 210000
E24: MOYENNE | F24: =AVERAGE(F11:F23) -> 118615.38
E25: TOTAL | F25: =SUM(F11:F23) -> 1542000

Sheet Achat
A1: MODULE ACHAT | M1: ='BDD unique'!A14 -> 1 | N1: ='BDD unique'!B14 -> Peugeot 406 | O1: =CONCATENATE(M1," : ",N1) -> 1 : Peugeot 406 | Q1: ='BDD unique'!A8 -> 6 | R1: ='BDD unique'!B8 -> Vaillant | S1: ='BDD unique'!C8 -> Paul | T1: =CONCATENATE(Q1," : ",R1," ",S1) -> 6 : Vaillant Paul
M2: ='BDD unique'!A15 -> 2 | N2: ='BDD unique'!B15 -> BMW série 3 | O2: =CONCATENATE(M2," : ",N2) -> 2 : BMW série 3 | Q2: ='BDD unique'!A9 -> 7 | R2: ='BDD unique'!B9 -> Faure | S2: ='BDD unique'!C9 -> Michel | T2: =CONCATENATE(Q2," : ",R2," ",S2) -> 7 : Faure Michel
A3: Sélectionnez le produit acheté | M3: ='BDD unique'!A16 -> 3 | N3: ='BDD unique'!B16 -> Renault mégane | O3: =CONCATENATE(M3," : ",N3) -> 3 : Renault mégane | Q3: ='BDD unique'!A10 -> 8 | R3: ='BDD unique'!B10 -> Huster | S3: ='BDD unique'!C10 -> Françis | T3: =CONCATENATE(Q3," : ",R3," ",S3) -> 8 : Huster Françis
A4: saisir la qté acheté | M4: ='BDD unique'!A17 -> 4 | N4: ='BDD unique'!B17 -> Renault clio | O4: =CONCATENATE(M4," : ",N4) -> 4 : Renault clio
A9: Historique des achats
A10: date vente | B10: n° produit acheté | C10: quantité acheté | D10: Prix unitaire achat | E10: Prix total
A11: 42006 | B11: 1 | C11: 20 | D11: =VLOOKUP(B11,'BDD unique'!$A$14:$D$17,4,FALSE()) -> 19000 | E11: =D11*C11 -> 380000
A12: 42009 | B12: 2 | C12: 20 | D12: =VLOOKUP(B12,'BDD unique'!$A$14:$D$17,4,FALSE()) -> 31000 | E12: =D12*C12 -> 620000
A13: 42010 | B13: 3 | C13: 20 | D13: =VLOOKUP(B13,'BDD unique'!$A$14:$D$17,4,FALSE()) -> 12000 | E13: =D13*C13 -> 240000
A14: 42010 | B14: 4 | C14: 20 | D14: =VLOOKUP(B14,'BDD unique'!$A$14:$D$17,4,FALSE()) -> 7000 | E14: =D14*C14 -> 140000
A15: 42011 | B15: 1 | C15: 10 | D15: =VLOOKUP(B15,'BDD unique'!$A$14:$D$17,4,FALSE()) -> 19000 | E15: =D15*C15 -> 190000
A16: 42020 | B16: 4 | C16: 13 | D16: =VLOOKUP(B16,'BDD unique'!$A$14:$D$17,4,FALSE()) -> 7000 | E16: =D16*C16 -> 91000
D20: MOYENNE | E20: =AVERAGE(E11:E16) -> 276833.33
D21: TOTAL | E21: =SUM(E11:E16) -> 1661000

Sheet Stock
A1: MODULE STOCK
A6: id produit | B6: nom produit | C6: Prix unitaire (achat) | D6: qté vendu | E6: qte acheté | F6: qté stock | G6: Valeur stock
A7: ='BDD unique'!A14 -> 1 | B7: ='BDD unique'!B14 -> Peugeot 406 | C7: ='BDD unique'!D14 -> 19000 | D7: =SUMIF(Vente!B:B,A7,Vente!C:C) -> 36 | E7: =SUMIF(Achat!B:B,A7,Achat!C:C) -> 30 | F7: =E7-D7 -> -6 | G7: =IF(F7<0,0,F7*C7) -> 0
A8: ='BDD unique'!A15 -> 2 | B8: ='BDD unique'!B15 -> BMW série 3 | C8: ='BDD unique'!D15 -> 31000 | D8: =SUMIF(Vente!B:B,A8,Vente!C:C) -> 8 | E8: =SUMIF(Achat!B:B,A8,Achat!C:C) -> 20 | F8: =E8-D8 -> 12 | G8: =IF(F8<0,0,F8*C8) -> 372000
A9: ='BDD unique'!A16 -> 3 | B9: ='BDD unique'!B16 -> Renault mégane | C9: ='BDD unique'!D16 -> 12000 | D9: =SUMIF(Vente!B:B,A9,Vente!C:C) -> 20 | E9: =SUMIF(Achat!B:B,A9,Achat!C:C) -> 20 | F9: =E9-D9 -> 0 | G9: =IF(F9<0,0,F9*C9) -> 0
A10: ='BDD unique'!A17 -> 4 | B10: ='BDD unique'!B17 -> Renault clio | C10: ='BDD unique'!D17 -> 7000 | D10: =SUMIF(Vente!B:B,A10,Vente!C:C) -> 23 | E10: =SUMIF(Achat!B:B,A10,Achat!C:C) -> 33 | F10: =E10-D10 -> 10 | G10: =IF(F10<0,0,F10*C10) -> 70000
F14: TOTAL | G14: =SUM(G7:G13) -> 442000

Sheet Finance
A1: MODULE FINANCE
A3: Année 2015
B5: Charge | C5: Recette
A6: Total des salaires | B6: =SUM('BDD unique'!F3:F10)*12 -> 382800
A7: Chiffre d'Affaire | C7: =Vente!F25 -> 1542000
A8: Achats | B8: =Achat!E21 -> 1661000
A9: Valeur stock | C9: =Stock!G14 -> 442000
A10: Divers charges | B10: =B8*5% -> 83050
A11: TOTAL | B11: =SUM(B6:B10) -> 2126850 | C11: =SUM(C6:C10) -> 1984000
A15: Résultat Net | B15: =C11-B11 -> -142850

Sheet Décisionnel
A1: MODULE Décisionnel (BI : BUSINESS INTELIGENCE) | M1: ='BDD unique'!A14 -> 1 | N1: ='BDD unique'!B14 -> Peugeot 406 | O1: =CONCATENATE(M1," : ",N1) -> 1 : Peugeot 406 | Q1: ='BDD unique'!A8 -> 6 | R1: ='BDD unique'!B8 -> Vaillant | S1: ='BDD unique'!C8 -> Paul | T1: =CONCATENATE(Q1," : ",R1," ",S1) -> 6 : Vaillant Paul
M2: ='BDD unique'!A15 -> 2 | N2: ='BDD unique'!B15 -> BMW série 3 | O2: =CONCATENATE(M2," : ",N2) -> 2 : BMW série 3 | Q2: ='BDD unique'!A9 -> 7 | R2: ='BDD unique'!B9 -> Faure | S2: ='BDD unique'!C9 -> Michel | T2: =CONCATENATE(Q2," : ",R2," ",S2) -> 7 : Faure Michel
A3: Ventes des vendeurs | M3: ='BDD unique'!A16 -> 3 | N3: ='BDD unique'!B16 -> Renault mégane | O3: =CONCATENATE(M3," : ",N3) -> 3 : Renault mégane | Q3: ='BDD unique'!A10 -> 8 | R3: ='BDD unique'!B10 -> Huster | S3: ='BDD unique'!C10 -> Françis | T3: =CONCATENATE(Q3," : ",R3," ",S3) -> 8 : Huster Françis
M4: ='BDD unique'!A17 -> 4 | N4: ='BDD unique'!B17 -> Renault clio | O4: =CONCATENATE(M4," : ",N4) -> 4 : Renault clio
C5: vendeur | D5: Total
C6: =T1 -> 6 : Vaillant Paul | D6: =SUMIF(Vente!D:D,Décisionnel!Q1,Vente!C:C) -> 46
C7: =T2 -> 7 : Faure Michel | D7: =SUMIF(Vente!D:D,Décisionnel!Q2,Vente!C:C) -> 16
C8: =T3 -> 8 : Huster Françis | D8: =SUMIF(Vente!D:D,Décisionnel!Q3,Vente!C:C) -> 25
A26: Voitures vendues
C28: Voiture | D28: Total
C29: =O1 -> 1 : Peugeot 406 | D29: =SUMIF(Vente!B:B,Décisionnel!M1,Vente!C:C) -> 36
C30: =O2 -> 2 : BMW série 3 | D30: =SUMIF(Vente!B:B,Décisionnel!M2,Vente!C:C) -> 8
C31: =O3 -> 3 : Renault mégane | D31: =SUMIF(Vente!B:B,Décisionnel!M3,Vente!C:C) -> 20
C32: =O4 -> 4 : Renault clio | D32: =SUMIF(Vente!B:B,Décisionnel!M4,Vente!C:C) -> 23
A50: Bénéfices par voiture
A52: Voiture | B52: Prix achat | C52: Prix vente | D52: Bénéfice pour 1 voiture vendue | E52: nb voiture vendue | F52: Bénéfice total
A53: =O1 -> 1 : Peugeot 406 | B53: ='BDD unique'!D14 -> 19000 | C53: ='BDD unique'!C14 -> 21000 | D53: =C53-B53 -> 2000 | E53: =D29 -> 36 | F53: =D53*E53 -> 72000
A54: =O2 -> 2 : BMW série 3 | B54: ='BDD unique'!D15 -> 31000 | C54: ='BDD unique'!C15 -> 32000 | D54: =C54-B54 -> 1000 | E54: =D30 -> 8 | F54: =D54*E54 -> 8000
A55: =O3 -> 3 : Renault mégane | B55: ='BDD unique'!D16 -> 12000 | C55: ='BDD unique'!C16 -> 15000 | D55: =C55-B55 -> 3000 | E55: =D31 -> 20 | F55: =D55*E55 -> 60000
A56: =O4 -> 4 : Renault clio | B56: ='BDD unique'!D17 -> 7000 | C56: ='BDD unique'!C17 -> 10000 | D56: =C56-B56 -> 3000 | E56: =D32 -> 23 | F56: =D56*E56 -> 69000
